pydiaid/__init__.py
pydiaid/cli.py
pydiaid/gui.py
pydiaid/loader.py
pydiaid/__pycache__/__init__.cpython-38.pyc
pydiaid/diapasef/__init__.py
pydiaid/diapasef/cli.py
pydiaid/diapasef/graphs.py
pydiaid/diapasef/gui_diapasef.py
pydiaid/diapasef/main.py
pydiaid/diapasef/method_creator.py
pydiaid/diapasef/method_evaluation.py
pydiaid/diapasef/method_optimizer.py
pydiaid/diapasef/static/AlphaPept_results.csv
pydiaid/diapasef/static/DIAParameterspy3TC.txt
pydiaid/diapasef/static/default_parameters.json
pydiaid/diapasef/static/diaPASEF_method.txt
pydiaid/docs/manual.docx
pydiaid/docs/manual.pdf
pydiaid/img/github.png
pydiaid/img/max-planck-gesellschaft.jpg
pydiaid/img/mpi_logo.png
pydiaid/oadia/gui_orbitrapastraldia.py
pydiaid/oadia/method_evaluation.py
pydiaid/oadia/method_generator.py
pydiaid/oadia/static/AlphaPept_results.csv
pydiaid/oadia/static/MassListTable_targeted.csv
pydiaid/oadia/static/default_parameters.json
pydiaid/style/dashboard_style.css
pydiaid/synchropasef/gui_synchropasef.py
pydiaid/synchropasef/loader_MS_parameter_file.py
pydiaid/synchropasef/method_creator.py
pydiaid/synchropasef/method_evaluator.py
pydiaid/synchropasef/plots.py
pydiaid/synchropasef/static/AlphaPept_results.csv
pydiaid/synchropasef/static/MaxQuant_Library.txt
pydiaid/synchropasef/static/default_parameters.json
pydiaid/synchropasef/static/evidence_MaxQuant_270223.txt
pydiaid/synchropasef/static/synchroScan.txt
pydiaid-0.0.40.dist-info/LICENSE.txt
pydiaid-0.0.40.dist-info/METADATA
pydiaid-0.0.40.dist-info/WHEEL
pydiaid-0.0.40.dist-info/entry_points.txt
pydiaid-0.0.40.dist-info/top_level.txt
pydiaid-0.0.40.dist-info/RECORD
